README.md
setup.py
italymusic/__init__.py
italymusic/__main__.py
italymusic/cli.py
italymusic/utils.py
italymusic.egg-info/PKG-INFO
italymusic.egg-info/SOURCES.txt
italymusic.egg-info/dependency_links.txt
italymusic.egg-info/entry_points.txt
italymusic.egg-info/requires.txt
italymusic.egg-info/top_level.txt
italymusic/handlers/PlaylistHandler.py
italymusic/handlers/URLHandler.py
italymusic/handlers/__init__.py
italymusic/services/AudioService.py
italymusic/services/DownloadService.py
italymusic/services/FileService.py
italymusic/services/SearchService.py
italymusic/services/TelegramService.py
italymusic/services/VideoService.py
italymusic/services/__init__.py
italymusic/telegram/TelegramYoutubeBot.py
italymusic/telegram/__init__.py
italymusic/tests/__init__.py
italymusic/tests/test_utils.py