Metadata-Version: 2.1
Name: italymusic
Version: 1.4.20
Summary: مكتبة لتحميل فيديوهات يوتيوب وتكاملها مع بوتات تليجرام
Home-page: UNKNOWN
Author: Italy Music
Author-email: hetari4all@gmail.com
License: MIT
Project-URL: Author, https://t.me/italy_5
Project-URL: Homepage, https://github.com/Hetari/pyutube
Project-URL: Bug Tracker, https://github.com/Hetari/pyutube/issues
Project-URL: Source Code, https://github.com/Hetari/pyutube
Project-URL: Documentation, https://github.com/Hetari/pyutube
Keywords: youtube,download,cli,italymusic,pytubefix,pytube,youtube-dl,telegram,pyrogram,bot
Platform: Linux
Platform: Windows
Platform: MacOS
Classifier: License :: OSI Approved :: MIT License
Classifier: Operating System :: OS Independent
Classifier: Programming Language :: Python :: 3
Requires-Python: >=3.6
